<odoo>
  <data>
    <!-- explicit list view definition -->
<!--
    <record model="ir.ui.view" id="pasajeros.list">
      <field name="name">pasajeros list</field>
      <field name="model">pasajeros.pasajeros</field>
      <field name="arch" type="xml">
        <tree>
          <field name="name"/>
          <field name="value"/>
          <field name="value2"/>
        </tree>
      </field>
    </record>
-->

    <!-- actions opening views on models -->
<!--
    <record model="ir.actions.act_window" id="pasajeros.action_window">
      <field name="name">pasajeros window</field>
      <field name="res_model">pasajeros.pasajeros</field>
      <field name="view_mode">tree,form</field>
    </record>
-->

    <!-- server action to the one above -->
<!--
    <record model="ir.actions.server" id="pasajeros.action_server">
      <field name="name">pasajeros server</field>
      <field name="model_id" ref="model_pasajeros_pasajeros"/>
      <field name="state">code</field>
      <field name="code">
        action = {
          "type": "ir.actions.act_window",
          "view_mode": "tree,form",
          "res_model": model._name,
        }
      </field>
    </record>
-->

    <!-- Top menu item -->
<!--
    <menuitem name="pasajeros" id="pasajeros.menu_root"/>
-->
    <!-- menu categories -->
<!--
    <menuitem name="Menu 1" id="pasajeros.menu_1" parent="pasajeros.menu_root"/>
    <menuitem name="Menu 2" id="pasajeros.menu_2" parent="pasajeros.menu_root"/>
-->
    <!-- actions -->
<!--
    <menuitem name="List" id="pasajeros.menu_1_list" parent="pasajeros.menu_1"
              action="pasajeros.action_window"/>
    <menuitem name="Server to list" id="pasajeros" parent="pasajeros.menu_2"
              action="pasajeros.action_server"/>
-->
  </data>
</odoo>